pyGenClean/__init__.py
pyGenClean/pipeline_error.py
pyGenClean/run_data_clean_up.py
pyGenClean/version.py
pyGenClean/Contamination/__init__.py
pyGenClean/Contamination/contamination.py
pyGenClean/DupSNPs/__init__.py
pyGenClean/DupSNPs/duplicated_snps.py
pyGenClean/DupSamples/__init__.py
pyGenClean/DupSamples/duplicated_samples.py
pyGenClean/Ethnicity/__init__.py
pyGenClean/Ethnicity/check_ethnicity.py
pyGenClean/Ethnicity/find_outliers.py
pyGenClean/Ethnicity/plot_eigenvalues.py
pyGenClean/FlagHW/__init__.py
pyGenClean/FlagHW/flag_hw.py
pyGenClean/FlagMAF/__init__.py
pyGenClean/FlagMAF/flag_maf_zero.py
pyGenClean/HeteroHap/__init__.py
pyGenClean/HeteroHap/remove_heterozygous_haploid.py
pyGenClean/LaTeX/__init__.py
pyGenClean/LaTeX/auto_report.py
pyGenClean/LaTeX/merge_reports.py
pyGenClean/LaTeX/utils.py
pyGenClean/LaTeX/templates/float_template.tex
pyGenClean/LaTeX/templates/graphics_template.tex
pyGenClean/LaTeX/templates/longtable_template.tex
pyGenClean/LaTeX/templates/main_document.tex
pyGenClean/LaTeX/templates/summary_table.tex
pyGenClean/LaTeX/templates/tabular_template.tex
pyGenClean/MarkerMissingness/__init__.py
pyGenClean/MarkerMissingness/snp_missingness.py
pyGenClean/Misc/__init__.py
pyGenClean/Misc/compare_gold_standard.py
pyGenClean/NoCallHetero/__init__.py
pyGenClean/NoCallHetero/clean_noCall_hetero_snps.py
pyGenClean/NoCallHetero/heterozygosity_plot.py
pyGenClean/PlateBias/__init__.py
pyGenClean/PlateBias/plate_bias.py
pyGenClean/PlinkUtils/__init__.py
pyGenClean/PlinkUtils/compare_bim.py
pyGenClean/PlinkUtils/plot_MDS.py
pyGenClean/PlinkUtils/plot_MDS_standalone.py
pyGenClean/PlinkUtils/subset_data.py
pyGenClean/RelatedSamples/__init__.py
pyGenClean/RelatedSamples/find_related_samples.py
pyGenClean/RelatedSamples/merge_related_samples.py
pyGenClean/SampleMissingness/__init__.py
pyGenClean/SampleMissingness/sample_missingness.py
pyGenClean/SexCheck/__init__.py
pyGenClean/SexCheck/baf_lrr_plot.py
pyGenClean-1.8.3.dist-info/DESCRIPTION.rst
pyGenClean-1.8.3.dist-info/METADATA
pyGenClean-1.8.3.dist-info/RECORD
pyGenClean-1.8.3.dist-info/WHEEL
pyGenClean-1.8.3.dist-info/entry_points.txt
pyGenClean-1.8.3.dist-info/metadata.json
pyGenClean-1.8.3.dist-info/pbr.json
pyGenClean-1.8.3.dist-info/top_level.txt
