Metadata-Version: 2.0
Name: pyGenClean
Version: 1.8.3
Summary: Automated data clean up pipeline for genetic data
Home-page: https://github.com/lemieuxl/pyGenClean
Author: Louis-Philippe Lemieux Perreault
Author-email: louis-philippe.lemieux.perreault@umontreal.ca
License: GPL
Keywords: bioinformatics quality control genetic
Platform: UNKNOWN
Classifier: Development Status :: 5 - Production/Stable
Classifier: Intended Audience :: Science/Research
Classifier: License :: OSI Approved :: GNU General Public License (GPL)
Classifier: Operating System :: Unix
Classifier: Operating System :: POSIX :: Linux
Classifier: Operating System :: MacOS :: MacOS X
Classifier: Operating System :: Microsoft :: Windows
Classifier: Programming Language :: Python
Classifier: Programming Language :: Python :: 2.7
Classifier: Topic :: Scientific/Engineering :: Bio-Informatics
Requires-Dist: matplotlib (>=1.2.0)
Requires-Dist: numpy (>=1.6.2)
Requires-Dist: scipy (>=0.11.0)
Requires-Dist: scikit-learn (>=0.12.1)
Requires-Dist: Jinja2 (>=2.7.3)
